pyhuff/__init__.py
pyhuff/classes.py
PythonHuff-1.0.4.dist-info/METADATA
PythonHuff-1.0.4.dist-info/WHEEL
PythonHuff-1.0.4.dist-info/entry_points.txt
PythonHuff-1.0.4.dist-info/top_level.txt
PythonHuff-1.0.4.dist-info/RECORD
