Metadata-Version: 2.1
Name: PythonHuff
Version: 1.0.4
Summary: Huffman compression and decompression (Pure Python implementation)
Home-page: UNKNOWN
License: UNKNOWN
Keywords: huffman,compression,decompression,algorithm
Platform: UNKNOWN
Classifier: Programming Language :: Python :: 3
Classifier: Programming Language :: Python :: 2
Classifier: Operating System :: OS Independent
